{
	"name": "Credits",
	"layers": [
		{
			"name": "Layer 0",
			"overriden": 0,
			"subLayers": [],
			"instances": [
				{
					"type": "DialogueBox",
					"properties": {
						"left-margin": 4,
						"right-margin": 4,
						"top-margin": 4,
						"bottom-margin": 4,
						"edges": "stretch",
						"fill": "stretch",
						"image-scale-x": 1,
						"image-scale-y": 1,
						"initially-visible": true,
						"origin": "top-left",
						"seams": "overlap"
					},
					"uid": 957,
					"sid": 650826498503130,
					"tags": "",
					"instanceVariables": {
						"Tag": ""
					},
					"behaviors": {},
					"showing": true,
					"locked": false,
					"world": {
						"x": 0,
						"y": 272,
						"width": 312,
						"height": 268,
						"originX": 0,
						"originY": 0,
						"color": [
							1,
							1,
							1,
							1
						],
						"angle": 0,
						"zElevation": 0
					}
				},
				{
					"type": "SpriteFont_Dialogue",
					"properties": {
						"text": "-----Created by Team Concha-----",
						"enable-bbcode": false,
						"character-width": 7,
						"character-height": 11,
						"character-set": " !\"   '`() +,-./0123456789:;<=>? ABCDEFGHIJKLMNOPQRSTUVWXYZ[\\]^_`abcdefghijklmnopqrstuvwxyz",
						"spacing-data": "",
						"scale": 1,
						"character-spacing": 0,
						"line-height": 0,
						"horizontal-alignment": "center",
						"vertical-alignment": "center",
						"wrapping": "word",
						"initially-visible": true,
						"origin": "top-left",
						"read-aloud": false
					},
					"uid": 958,
					"sid": 915874657293727,
					"tags": "",
					"instanceVariables": {
						"Tag": ""
					},
					"behaviors": {
						"Flash": {
							"properties": {}
						}
					},
					"effects": {
						"Tint": {
							"isEnabled": true,
							"parameters": {
								"color": [
									1,
									1,
									1,
									1
								]
							}
						}
					},
					"showing": true,
					"locked": false,
					"world": {
						"x": 0,
						"y": 244,
						"width": 312,
						"height": 16,
						"originX": 0,
						"originY": 0,
						"color": [
							1,
							1,
							1,
							1
						],
						"angle": 0,
						"zElevation": 0
					}
				},
				{
					"type": "SpriteFont_Dialogue",
					"properties": {
						"text": "Enzo Cantoni",
						"enable-bbcode": false,
						"character-width": 7,
						"character-height": 11,
						"character-set": " !\"   '`() +,-./0123456789:;<=>? ABCDEFGHIJKLMNOPQRSTUVWXYZ[\\]^_`abcdefghijklmnopqrstuvwxyz",
						"spacing-data": "",
						"scale": 1,
						"character-spacing": 0,
						"line-height": 0,
						"horizontal-alignment": "center",
						"vertical-alignment": "center",
						"wrapping": "word",
						"initially-visible": true,
						"origin": "top-left",
						"read-aloud": false
					},
					"uid": 959,
					"sid": 946699145057104,
					"tags": "",
					"instanceVariables": {
						"Tag": ""
					},
					"behaviors": {
						"Flash": {
							"properties": {}
						}
					},
					"effects": {
						"Tint": {
							"isEnabled": true,
							"parameters": {
								"color": [
									0.10196078431372549,
									0.9921568627450981,
									0,
									1
								]
							}
						}
					},
					"showing": true,
					"locked": false,
					"world": {
						"x": 0,
						"y": 276,
						"width": 312,
						"height": 16,
						"originX": 0,
						"originY": 0,
						"color": [
							1,
							1,
							1,
							1
						],
						"angle": 0,
						"zElevation": 0
					}
				},
				{
					"type": "SpriteFont_Dialogue",
					"properties": {
						"text": "Adrian Cabrera",
						"enable-bbcode": false,
						"character-width": 7,
						"character-height": 11,
						"character-set": " !\"   '`() +,-./0123456789:;<=>? ABCDEFGHIJKLMNOPQRSTUVWXYZ[\\]^_`abcdefghijklmnopqrstuvwxyz",
						"spacing-data": "",
						"scale": 1,
						"character-spacing": 0,
						"line-height": 0,
						"horizontal-alignment": "center",
						"vertical-alignment": "center",
						"wrapping": "word",
						"initially-visible": true,
						"origin": "top-left",
						"read-aloud": false
					},
					"uid": 961,
					"sid": 903741633248715,
					"tags": "",
					"instanceVariables": {
						"Tag": ""
					},
					"behaviors": {
						"Flash": {
							"properties": {}
						}
					},
					"effects": {
						"Tint": {
							"isEnabled": true,
							"parameters": {
								"color": [
									0.9450980392156862,
									0.5215686274509804,
									0.23921568627450981,
									1
								]
							}
						}
					},
					"showing": true,
					"locked": false,
					"world": {
						"x": 0,
						"y": 328,
						"width": 312,
						"height": 16,
						"originX": 0,
						"originY": 0,
						"color": [
							1,
							1,
							1,
							1
						],
						"angle": 0,
						"zElevation": 0
					}
				},
				{
					"type": "SpriteFont_Dialogue",
					"properties": {
						"text": "Juan Parra",
						"enable-bbcode": false,
						"character-width": 7,
						"character-height": 11,
						"character-set": " !\"   '`() +,-./0123456789:;<=>? ABCDEFGHIJKLMNOPQRSTUVWXYZ[\\]^_`abcdefghijklmnopqrstuvwxyz",
						"spacing-data": "",
						"scale": 1,
						"character-spacing": 0,
						"line-height": 0,
						"horizontal-alignment": "center",
						"vertical-alignment": "center",
						"wrapping": "word",
						"initially-visible": true,
						"origin": "top-left",
						"read-aloud": false
					},
					"uid": 963,
					"sid": 483131658271066,
					"tags": "",
					"instanceVariables": {
						"Tag": ""
					},
					"behaviors": {
						"Flash": {
							"properties": {}
						}
					},
					"effects": {
						"Tint": {
							"isEnabled": true,
							"parameters": {
								"color": [
									0.9568627450980393,
									0.9725490196078431,
									0.38823529411764707,
									1
								]
							}
						}
					},
					"showing": true,
					"locked": false,
					"world": {
						"x": 0,
						"y": 380,
						"width": 312,
						"height": 16,
						"originX": 0,
						"originY": 0,
						"color": [
							1,
							1,
							1,
							1
						],
						"angle": 0,
						"zElevation": 0
					}
				},
				{
					"type": "SpriteFont_Dialogue",
					"properties": {
						"text": "Using DEMONOIRE template with Construct3",
						"enable-bbcode": false,
						"character-width": 7,
						"character-height": 11,
						"character-set": " !\"   '`() +,-./0123456789:;<=>? ABCDEFGHIJKLMNOPQRSTUVWXYZ[\\]^_`abcdefghijklmnopqrstuvwxyz",
						"spacing-data": "",
						"scale": 1,
						"character-spacing": 0,
						"line-height": 0,
						"horizontal-alignment": "left",
						"vertical-alignment": "center",
						"wrapping": "word",
						"initially-visible": true,
						"origin": "top-left",
						"read-aloud": false
					},
					"uid": 966,
					"sid": 421897461044164,
					"tags": "",
					"instanceVariables": {
						"Tag": ""
					},
					"behaviors": {
						"Flash": {
							"properties": {}
						}
					},
					"effects": {
						"Tint": {
							"isEnabled": true,
							"parameters": {
								"color": [
									1,
									1,
									1,
									1
								]
							}
						}
					},
					"showing": true,
					"locked": false,
					"world": {
						"x": 8,
						"y": 584,
						"width": 312,
						"height": 24,
						"originX": 0,
						"originY": 0,
						"color": [
							1,
							1,
							1,
							1
						],
						"angle": 0,
						"zElevation": 0
					}
				},
				{
					"type": "SpriteFont_Dialogue",
					"properties": {
						"text": "(Red Social)",
						"enable-bbcode": false,
						"character-width": 7,
						"character-height": 11,
						"character-set": " !\"   '`() +,-./0123456789:;<=>? ABCDEFGHIJKLMNOPQRSTUVWXYZ[\\]^_`abcdefghijklmnopqrstuvwxyz",
						"spacing-data": "",
						"scale": 1,
						"character-spacing": 0,
						"line-height": 0,
						"horizontal-alignment": "left",
						"vertical-alignment": "center",
						"wrapping": "word",
						"initially-visible": true,
						"origin": "top-left",
						"read-aloud": false
					},
					"uid": 967,
					"sid": 623579124974174,
					"tags": "",
					"instanceVariables": {
						"Tag": ""
					},
					"behaviors": {
						"Flash": {
							"properties": {}
						}
					},
					"effects": {
						"Tint": {
							"isEnabled": true,
							"parameters": {
								"color": [
									0.10196078431372549,
									0.9921568627450981,
									0,
									1
								]
							}
						}
					},
					"showing": true,
					"locked": false,
					"world": {
						"x": 8,
						"y": 600,
						"width": 312,
						"height": 24,
						"originX": 0,
						"originY": 0,
						"color": [
							1,
							1,
							1,
							1
						],
						"angle": 0,
						"zElevation": 0
					}
				},
				{
					"type": "SpriteFont_Dialogue",
					"properties": {
						"text": "(Red Social)",
						"enable-bbcode": false,
						"character-width": 7,
						"character-height": 11,
						"character-set": " !\"   '`() +,-./0123456789:;<=>? ABCDEFGHIJKLMNOPQRSTUVWXYZ[\\]^_`abcdefghijklmnopqrstuvwxyz",
						"spacing-data": "",
						"scale": 1,
						"character-spacing": 0,
						"line-height": 0,
						"horizontal-alignment": "left",
						"vertical-alignment": "center",
						"wrapping": "word",
						"initially-visible": true,
						"origin": "top-left",
						"read-aloud": false
					},
					"uid": 970,
					"sid": 715237564861458,
					"tags": "",
					"instanceVariables": {
						"Tag": "EndCredits"
					},
					"behaviors": {
						"Flash": {
							"properties": {}
						}
					},
					"effects": {
						"Tint": {
							"isEnabled": true,
							"parameters": {
								"color": [
									0.9450980392156862,
									0.5215686274509804,
									0.23921568627450981,
									1
								]
							}
						}
					},
					"showing": true,
					"locked": false,
					"world": {
						"x": 8,
						"y": 616,
						"width": 312,
						"height": 24,
						"originX": 0,
						"originY": 0,
						"color": [
							1,
							1,
							1,
							1
						],
						"angle": 0,
						"zElevation": 0
					}
				},
				{
					"type": "SpriteFont_Tiny",
					"properties": {
						"text": "SPECIAL THANKS TO\n\n♥ GARCIA MORUECO LLUIS",
						"enable-bbcode": false,
						"character-width": 8,
						"character-height": 8,
						"character-set": "ABCDEFGHIJKLMNOPQRSTUVWXYZ()♥☻•",
						"spacing-data": "",
						"scale": 1,
						"character-spacing": -3,
						"line-height": 0,
						"horizontal-alignment": "right",
						"vertical-alignment": "bottom",
						"wrapping": "word",
						"initially-visible": true,
						"origin": "top-left",
						"read-aloud": false
					},
					"uid": 972,
					"sid": 872181363032790,
					"tags": "",
					"instanceVariables": {},
					"behaviors": {},
					"effects": {
						"Tint": {
							"isEnabled": true,
							"parameters": {
								"color": [
									0.5254901960784314,
									0.5254901960784314,
									0.5254901960784314,
									1
								]
							}
						}
					},
					"showing": true,
					"locked": false,
					"world": {
						"x": 148,
						"y": 584,
						"width": 160,
						"height": 52,
						"originX": 0,
						"originY": 0,
						"color": [
							1,
							1,
							1,
							1
						],
						"angle": 0,
						"zElevation": 0
					}
				},
				{
					"type": "SpriteFont_Tiny",
					"properties": {
						"text": "PROGRAMMING • GAME DESIGN • LEVEL DESIGN",
						"enable-bbcode": false,
						"character-width": 8,
						"character-height": 8,
						"character-set": "ABCDEFGHIJKLMNOPQRSTUVWXYZ()♥☻•",
						"spacing-data": "",
						"scale": 1,
						"character-spacing": -3,
						"line-height": 0,
						"horizontal-alignment": "center",
						"vertical-alignment": "bottom",
						"wrapping": "word",
						"initially-visible": true,
						"origin": "top-left",
						"read-aloud": false
					},
					"uid": 978,
					"sid": 337126572243074,
					"tags": "",
					"instanceVariables": {},
					"behaviors": {},
					"effects": {
						"Tint": {
							"isEnabled": true,
							"parameters": {
								"color": [
									1,
									1,
									1,
									1
								]
							}
						}
					},
					"showing": true,
					"locked": false,
					"world": {
						"x": 0,
						"y": 296,
						"width": 312,
						"height": 12,
						"originX": 0,
						"originY": 0,
						"color": [
							1,
							1,
							1,
							1
						],
						"angle": 0,
						"zElevation": 0
					}
				},
				{
					"type": "SpriteFont_Tiny",
					"properties": {
						"text": "PROGRAMMING • SPRITES • GAME DESIGN",
						"enable-bbcode": false,
						"character-width": 8,
						"character-height": 8,
						"character-set": "ABCDEFGHIJKLMNOPQRSTUVWXYZ()♥☻•",
						"spacing-data": "",
						"scale": 1,
						"character-spacing": -3,
						"line-height": 0,
						"horizontal-alignment": "center",
						"vertical-alignment": "bottom",
						"wrapping": "word",
						"initially-visible": true,
						"origin": "top-left",
						"read-aloud": false
					},
					"uid": 979,
					"sid": 523061001330299,
					"tags": "",
					"instanceVariables": {},
					"behaviors": {},
					"effects": {
						"Tint": {
							"isEnabled": true,
							"parameters": {
								"color": [
									1,
									1,
									1,
									1
								]
							}
						}
					},
					"showing": true,
					"locked": false,
					"world": {
						"x": 0,
						"y": 348,
						"width": 312,
						"height": 12,
						"originX": 0,
						"originY": 0,
						"color": [
							1,
							1,
							1,
							1
						],
						"angle": 0,
						"zElevation": 0
					}
				},
				{
					"type": "SpriteFont_Tiny",
					"properties": {
						"text": "LEVEL DESIGN • GAME DESIGN • SCRIPTS",
						"enable-bbcode": false,
						"character-width": 8,
						"character-height": 8,
						"character-set": "ABCDEFGHIJKLMNOPQRSTUVWXYZ()♥☻•",
						"spacing-data": "",
						"scale": 1,
						"character-spacing": -3,
						"line-height": 0,
						"horizontal-alignment": "center",
						"vertical-alignment": "bottom",
						"wrapping": "word",
						"initially-visible": true,
						"origin": "top-left",
						"read-aloud": false
					},
					"uid": 981,
					"sid": 204502424883633,
					"tags": "",
					"instanceVariables": {},
					"behaviors": {},
					"effects": {
						"Tint": {
							"isEnabled": true,
							"parameters": {
								"color": [
									1,
									1,
									1,
									1
								]
							}
						}
					},
					"showing": true,
					"locked": false,
					"world": {
						"x": 0,
						"y": 404,
						"width": 312,
						"height": 12,
						"originX": 0,
						"originY": 0,
						"color": [
							1,
							1,
							1,
							1
						],
						"angle": 0,
						"zElevation": 0
					}
				},
				{
					"type": "SpriteFont_Dialogue",
					"properties": {
						"text": "Alissa Zuniga",
						"enable-bbcode": false,
						"character-width": 7,
						"character-height": 11,
						"character-set": " !\"   '`() +,-./0123456789:;<=>? ABCDEFGHIJKLMNOPQRSTUVWXYZ[\\]^_`abcdefghijklmnopqrstuvwxyz",
						"spacing-data": "",
						"scale": 1,
						"character-spacing": 0,
						"line-height": 0,
						"horizontal-alignment": "center",
						"vertical-alignment": "center",
						"wrapping": "word",
						"initially-visible": true,
						"origin": "top-left",
						"read-aloud": false
					},
					"uid": 984,
					"sid": 727429290086572,
					"tags": "",
					"instanceVariables": {
						"Tag": ""
					},
					"behaviors": {
						"Flash": {
							"properties": {}
						}
					},
					"effects": {
						"Tint": {
							"isEnabled": true,
							"parameters": {
								"color": [
									0.9568627450980393,
									0.9725490196078431,
									0.38823529411764707,
									1
								]
							}
						}
					},
					"showing": true,
					"locked": false,
					"world": {
						"x": 0,
						"y": 432,
						"width": 312,
						"height": 16,
						"originX": 0,
						"originY": 0,
						"color": [
							1,
							1,
							1,
							1
						],
						"angle": 0,
						"zElevation": 0
					}
				},
				{
					"type": "SpriteFont_Dialogue",
					"properties": {
						"text": "Lucia Baquero",
						"enable-bbcode": false,
						"character-width": 7,
						"character-height": 11,
						"character-set": " !\"   '`() +,-./0123456789:;<=>? ABCDEFGHIJKLMNOPQRSTUVWXYZ[\\]^_`abcdefghijklmnopqrstuvwxyz",
						"spacing-data": "",
						"scale": 1,
						"character-spacing": 0,
						"line-height": 0,
						"horizontal-alignment": "center",
						"vertical-alignment": "center",
						"wrapping": "word",
						"initially-visible": true,
						"origin": "top-left",
						"read-aloud": false
					},
					"uid": 985,
					"sid": 334764763521942,
					"tags": "",
					"instanceVariables": {
						"Tag": ""
					},
					"behaviors": {
						"Flash": {
							"properties": {}
						}
					},
					"effects": {
						"Tint": {
							"isEnabled": true,
							"parameters": {
								"color": [
									0.9568627450980393,
									0.9725490196078431,
									0.38823529411764707,
									1
								]
							}
						}
					},
					"showing": true,
					"locked": false,
					"world": {
						"x": 0,
						"y": 468,
						"width": 312,
						"height": 16,
						"originX": 0,
						"originY": 0,
						"color": [
							1,
							1,
							1,
							1
						],
						"angle": 0,
						"zElevation": 0
					}
				},
				{
					"type": "SpriteFont_Dialogue",
					"properties": {
						"text": "Ray",
						"enable-bbcode": false,
						"character-width": 7,
						"character-height": 11,
						"character-set": " !\"   '`() +,-./0123456789:;<=>? ABCDEFGHIJKLMNOPQRSTUVWXYZ[\\]^_`abcdefghijklmnopqrstuvwxyz",
						"spacing-data": "",
						"scale": 1,
						"character-spacing": 0,
						"line-height": 0,
						"horizontal-alignment": "center",
						"vertical-alignment": "center",
						"wrapping": "word",
						"initially-visible": true,
						"origin": "top-left",
						"read-aloud": false
					},
					"uid": 986,
					"sid": 958346984097908,
					"tags": "",
					"instanceVariables": {
						"Tag": ""
					},
					"behaviors": {
						"Flash": {
							"properties": {}
						}
					},
					"effects": {
						"Tint": {
							"isEnabled": true,
							"parameters": {
								"color": [
									0.9568627450980393,
									0.9725490196078431,
									0.38823529411764707,
									1
								]
							}
						}
					},
					"showing": true,
					"locked": false,
					"world": {
						"x": 0,
						"y": 500,
						"width": 312,
						"height": 16,
						"originX": 0,
						"originY": 0,
						"color": [
							1,
							1,
							1,
							1
						],
						"angle": 0,
						"zElevation": 0
					}
				},
				{
					"type": "SpriteFont_Tiny",
					"properties": {
						"text": "PROGAMMING • LEVEL DESIGN ",
						"enable-bbcode": false,
						"character-width": 8,
						"character-height": 8,
						"character-set": "ABCDEFGHIJKLMNOPQRSTUVWXYZ()♥☻•",
						"spacing-data": "",
						"scale": 1,
						"character-spacing": -3,
						"line-height": 0,
						"horizontal-alignment": "center",
						"vertical-alignment": "bottom",
						"wrapping": "word",
						"initially-visible": true,
						"origin": "top-left",
						"read-aloud": false
					},
					"uid": 988,
					"sid": 260196403035504,
					"tags": "",
					"instanceVariables": {},
					"behaviors": {},
					"effects": {
						"Tint": {
							"isEnabled": true,
							"parameters": {
								"color": [
									1,
									1,
									1,
									1
								]
							}
						}
					},
					"showing": true,
					"locked": false,
					"world": {
						"x": 0,
						"y": 448,
						"width": 312,
						"height": 12,
						"originX": 0,
						"originY": 0,
						"color": [
							1,
							1,
							1,
							1
						],
						"angle": 0,
						"zElevation": 0
					}
				},
				{
					"type": "SpriteFont_Tiny",
					"properties": {
						"text": " • TITLE • CONCEPT ART",
						"enable-bbcode": false,
						"character-width": 8,
						"character-height": 8,
						"character-set": "ABCDEFGHIJKLMNOPQRSTUVWXYZ()♥☻•",
						"spacing-data": "",
						"scale": 1,
						"character-spacing": -3,
						"line-height": 0,
						"horizontal-alignment": "center",
						"vertical-alignment": "bottom",
						"wrapping": "word",
						"initially-visible": true,
						"origin": "top-left",
						"read-aloud": false
					},
					"uid": 989,
					"sid": 648474254736694,
					"tags": "",
					"instanceVariables": {},
					"behaviors": {},
					"effects": {
						"Tint": {
							"isEnabled": true,
							"parameters": {
								"color": [
									1,
									1,
									1,
									1
								]
							}
						}
					},
					"showing": true,
					"locked": false,
					"world": {
						"x": 0,
						"y": 484,
						"width": 312,
						"height": 12,
						"originX": 0,
						"originY": 0,
						"color": [
							1,
							1,
							1,
							1
						],
						"angle": 0,
						"zElevation": 0
					}
				},
				{
					"type": "SpriteFont_Tiny",
					"properties": {
						"text": " • MUSIC •",
						"enable-bbcode": false,
						"character-width": 8,
						"character-height": 8,
						"character-set": "ABCDEFGHIJKLMNOPQRSTUVWXYZ()♥☻•",
						"spacing-data": "",
						"scale": 1,
						"character-spacing": -3,
						"line-height": 0,
						"horizontal-alignment": "center",
						"vertical-alignment": "bottom",
						"wrapping": "word",
						"initially-visible": true,
						"origin": "top-left",
						"read-aloud": false
					},
					"uid": 990,
					"sid": 358369024139509,
					"tags": "",
					"instanceVariables": {},
					"behaviors": {},
					"effects": {
						"Tint": {
							"isEnabled": true,
							"parameters": {
								"color": [
									1,
									1,
									1,
									1
								]
							}
						}
					},
					"showing": true,
					"locked": false,
					"world": {
						"x": 0,
						"y": 520,
						"width": 312,
						"height": 12,
						"originX": 0,
						"originY": 0,
						"color": [
							1,
							1,
							1,
							1
						],
						"angle": 0,
						"zElevation": 0
					}
				}
			],
			"sid": 235929144114418,
			"effectTypes": [],
			"isInitiallyVisible": true,
			"isInitiallyInteractive": true,
			"isHTMLElementsLayer": false,
			"color": [
				1,
				1,
				1,
				1
			],
			"backgroundColor": [
				0.0392156862745098,
				0.0392156862745098,
				0.0392156862745098,
				1
			],
			"isTransparent": false,
			"parallaxX": 1,
			"parallaxY": 1,
			"scaleRate": 1,
			"forceOwnTexture": false,
			"renderingMode": "3d",
			"drawOrder": "z-order",
			"useRenderCells": false,
			"blendMode": "normal",
			"zElevation": 0,
			"global": false
		}
	],
	"scene-graphs-folder-root": {
		"items": [],
		"subfolders": []
	},
	"sid": 241564524632102,
	"nonworld-instances": [],
	"effectTypes": [],
	"width": 312,
	"height": 240,
	"unboundedScrolling": false,
	"vpX": 0.5,
	"vpY": 0.5,
	"projection": "perspective",
	"eventSheet": "eCredits"
}