{
	"name": "En_RangeGuard_Mask",
	"plugin-id": "Sprite",
	"sid": 329224236204222,
	"isGlobal": false,
	"editorNewInstanceIsReplica": true,
	"instanceVariables": [
		{
			"name": "State",
			"type": "string",
			"desc": "",
			"show": true,
			"sid": 443934905891190
		},
		{
			"name": "State_Timer",
			"type": "number",
			"desc": "",
			"show": true,
			"sid": 935758236361098
		},
		{
			"name": "StateLimit",
			"type": "number",
			"desc": "",
			"show": true,
			"sid": 229813553110396
		}
	],
	"behaviorTypes": [],
	"effectTypes": [],
	"animations": {
		"items": [
			{
				"frames": [
					{
						"width": 48,
						"height": 48,
						"originX": 0.5,
						"originY": 0.8125,
						"originalSource": "",
						"exportFormat": "lossless",
						"exportQuality": 0.8,
						"fileType": "image/png",
						"imageSpriteId": 6971700,
						"useCollisionPoly": true,
						"duration": 1,
						"tag": ""
					},
					{
						"width": 48,
						"height": 48,
						"originX": 0.5,
						"originY": 0.8125,
						"originalSource": "",
						"exportFormat": "lossless",
						"exportQuality": 0.8,
						"fileType": "image/png",
						"imageSpriteId": 9896023,
						"useCollisionPoly": true,
						"duration": 1,
						"tag": ""
					},
					{
						"width": 48,
						"height": 48,
						"originX": 0.5,
						"originY": 0.8125,
						"originalSource": "",
						"exportFormat": "lossless",
						"exportQuality": 0.8,
						"fileType": "image/png",
						"imageSpriteId": 7746741,
						"useCollisionPoly": true,
						"duration": 1,
						"tag": ""
					},
					{
						"width": 48,
						"height": 48,
						"originX": 0.5,
						"originY": 0.8125,
						"originalSource": "",
						"exportFormat": "lossless",
						"exportQuality": 0.8,
						"fileType": "image/png",
						"imageSpriteId": 3581676,
						"useCollisionPoly": true,
						"duration": 1,
						"tag": ""
					}
				],
				"sid": 894711485315941,
				"name": "Idle_Down",
				"isLooping": true,
				"isPingPong": false,
				"repeatCount": 1,
				"repeatTo": 0,
				"speed": 5
			},
			{
				"frames": [
					{
						"width": 48,
						"height": 48,
						"originX": 0.5,
						"originY": 0.8125,
						"originalSource": "",
						"exportFormat": "lossless",
						"exportQuality": 0.8,
						"fileType": "image/png",
						"imageSpriteId": 1082040,
						"useCollisionPoly": true,
						"duration": 1,
						"tag": ""
					},
					{
						"width": 48,
						"height": 48,
						"originX": 0.5,
						"originY": 0.8125,
						"originalSource": "",
						"exportFormat": "lossless",
						"exportQuality": 0.8,
						"fileType": "image/png",
						"imageSpriteId": 3598363,
						"useCollisionPoly": true,
						"duration": 1,
						"tag": ""
					},
					{
						"width": 48,
						"height": 48,
						"originX": 0.5,
						"originY": 0.8125,
						"originalSource": "",
						"exportFormat": "lossless",
						"exportQuality": 0.8,
						"fileType": "image/png",
						"imageSpriteId": 1716964,
						"useCollisionPoly": true,
						"duration": 1,
						"tag": ""
					},
					{
						"width": 48,
						"height": 48,
						"originX": 0.5,
						"originY": 0.8125,
						"originalSource": "",
						"exportFormat": "lossless",
						"exportQuality": 0.8,
						"fileType": "image/png",
						"imageSpriteId": 8764492,
						"useCollisionPoly": true,
						"duration": 1,
						"tag": ""
					},
					{
						"width": 48,
						"height": 48,
						"originX": 0.5,
						"originY": 0.8125,
						"originalSource": "",
						"exportFormat": "lossless",
						"exportQuality": 0.8,
						"fileType": "image/png",
						"imageSpriteId": 3270631,
						"useCollisionPoly": true,
						"duration": 1,
						"tag": ""
					}
				],
				"sid": 353755716029410,
				"name": "Idle_Up",
				"isLooping": true,
				"isPingPong": false,
				"repeatCount": 1,
				"repeatTo": 0,
				"speed": 5
			},
			{
				"frames": [
					{
						"width": 48,
						"height": 48,
						"originX": 0.5,
						"originY": 0.8125,
						"originalSource": "",
						"exportFormat": "lossless",
						"exportQuality": 0.8,
						"fileType": "image/png",
						"imageSpriteId": 3530566,
						"useCollisionPoly": true,
						"duration": 1,
						"tag": ""
					},
					{
						"width": 48,
						"height": 48,
						"originX": 0.5,
						"originY": 0.8125,
						"originalSource": "",
						"exportFormat": "lossless",
						"exportQuality": 0.8,
						"fileType": "image/png",
						"imageSpriteId": 7639863,
						"useCollisionPoly": true,
						"duration": 1,
						"tag": ""
					},
					{
						"width": 48,
						"height": 48,
						"originX": 0.5,
						"originY": 0.8125,
						"originalSource": "",
						"exportFormat": "lossless",
						"exportQuality": 0.8,
						"fileType": "image/png",
						"imageSpriteId": 747757,
						"useCollisionPoly": true,
						"duration": 1,
						"tag": ""
					},
					{
						"width": 48,
						"height": 48,
						"originX": 0.5,
						"originY": 0.8125,
						"originalSource": "",
						"exportFormat": "lossless",
						"exportQuality": 0.8,
						"fileType": "image/png",
						"imageSpriteId": 79092,
						"useCollisionPoly": true,
						"duration": 1,
						"tag": ""
					},
					{
						"width": 48,
						"height": 48,
						"originX": 0.5,
						"originY": 0.8125,
						"originalSource": "",
						"exportFormat": "lossless",
						"exportQuality": 0.8,
						"fileType": "image/png",
						"imageSpriteId": 4736407,
						"useCollisionPoly": true,
						"duration": 1,
						"tag": ""
					}
				],
				"sid": 740755224128919,
				"name": "Idle_Left",
				"isLooping": true,
				"isPingPong": false,
				"repeatCount": 1,
				"repeatTo": 0,
				"speed": 5
			},
			{
				"frames": [
					{
						"width": 48,
						"height": 48,
						"originX": 0.5,
						"originY": 0.8125,
						"originalSource": "",
						"exportFormat": "lossless",
						"exportQuality": 0.8,
						"fileType": "image/png",
						"imageSpriteId": 5476387,
						"useCollisionPoly": true,
						"duration": 1,
						"tag": ""
					},
					{
						"width": 48,
						"height": 48,
						"originX": 0.5,
						"originY": 0.8125,
						"originalSource": "",
						"exportFormat": "lossless",
						"exportQuality": 0.8,
						"fileType": "image/png",
						"imageSpriteId": 5244334,
						"useCollisionPoly": true,
						"duration": 1,
						"tag": ""
					},
					{
						"width": 48,
						"height": 48,
						"originX": 0.5,
						"originY": 0.8125,
						"originalSource": "",
						"exportFormat": "lossless",
						"exportQuality": 0.8,
						"fileType": "image/png",
						"imageSpriteId": 6798542,
						"useCollisionPoly": true,
						"duration": 1,
						"tag": ""
					},
					{
						"width": 48,
						"height": 48,
						"originX": 0.5,
						"originY": 0.8125,
						"originalSource": "",
						"exportFormat": "lossless",
						"exportQuality": 0.8,
						"fileType": "image/png",
						"imageSpriteId": 2974118,
						"useCollisionPoly": true,
						"duration": 1,
						"tag": ""
					},
					{
						"width": 48,
						"height": 48,
						"originX": 0.5,
						"originY": 0.8125,
						"originalSource": "",
						"exportFormat": "lossless",
						"exportQuality": 0.8,
						"fileType": "image/png",
						"imageSpriteId": 5214694,
						"useCollisionPoly": true,
						"duration": 1,
						"tag": ""
					}
				],
				"sid": 232023598731571,
				"name": "Idle_Right",
				"isLooping": true,
				"isPingPong": false,
				"repeatCount": 1,
				"repeatTo": 0,
				"speed": 5
			},
			{
				"frames": [
					{
						"width": 48,
						"height": 48,
						"originX": 0.5,
						"originY": 0.8125,
						"originalSource": "",
						"exportFormat": "lossless",
						"exportQuality": 0.8,
						"fileType": "image/png",
						"imageSpriteId": 9001445,
						"useCollisionPoly": true,
						"duration": 1,
						"tag": ""
					},
					{
						"width": 48,
						"height": 48,
						"originX": 0.5,
						"originY": 0.8125,
						"originalSource": "",
						"exportFormat": "lossless",
						"exportQuality": 0.8,
						"fileType": "image/png",
						"imageSpriteId": 3319686,
						"useCollisionPoly": true,
						"duration": 1,
						"tag": ""
					},
					{
						"width": 48,
						"height": 48,
						"originX": 0.5,
						"originY": 0.8125,
						"originalSource": "",
						"exportFormat": "lossless",
						"exportQuality": 0.8,
						"fileType": "image/png",
						"imageSpriteId": 1305390,
						"useCollisionPoly": true,
						"duration": 1,
						"tag": ""
					},
					{
						"width": 48,
						"height": 48,
						"originX": 0.5,
						"originY": 0.8125,
						"originalSource": "",
						"exportFormat": "lossless",
						"exportQuality": 0.8,
						"fileType": "image/png",
						"imageSpriteId": 3424747,
						"useCollisionPoly": true,
						"duration": 1,
						"tag": ""
					}
				],
				"sid": 134563820273630,
				"name": "Walk_Left",
				"isLooping": true,
				"isPingPong": false,
				"repeatCount": 1,
				"repeatTo": 0,
				"speed": 13
			},
			{
				"frames": [
					{
						"width": 48,
						"height": 48,
						"originX": 0.5,
						"originY": 0.8125,
						"originalSource": "",
						"exportFormat": "lossless",
						"exportQuality": 0.8,
						"fileType": "image/png",
						"imageSpriteId": 4797585,
						"useCollisionPoly": true,
						"duration": 1,
						"tag": ""
					},
					{
						"width": 48,
						"height": 48,
						"originX": 0.5,
						"originY": 0.8125,
						"originalSource": "",
						"exportFormat": "lossless",
						"exportQuality": 0.8,
						"fileType": "image/png",
						"imageSpriteId": 9815913,
						"useCollisionPoly": true,
						"duration": 1,
						"tag": ""
					},
					{
						"width": 48,
						"height": 48,
						"originX": 0.5,
						"originY": 0.8125,
						"originalSource": "",
						"exportFormat": "lossless",
						"exportQuality": 0.8,
						"fileType": "image/png",
						"imageSpriteId": 6794275,
						"useCollisionPoly": true,
						"duration": 1,
						"tag": ""
					},
					{
						"width": 48,
						"height": 48,
						"originX": 0.5,
						"originY": 0.8125,
						"originalSource": "",
						"exportFormat": "lossless",
						"exportQuality": 0.8,
						"fileType": "image/png",
						"imageSpriteId": 6622736,
						"useCollisionPoly": true,
						"duration": 1,
						"tag": ""
					}
				],
				"sid": 899825968345830,
				"name": "Walk_Right",
				"isLooping": true,
				"isPingPong": false,
				"repeatCount": 1,
				"repeatTo": 0,
				"speed": 13
			},
			{
				"frames": [
					{
						"width": 48,
						"height": 48,
						"originX": 0.5,
						"originY": 0.8125,
						"originalSource": "",
						"exportFormat": "lossless",
						"exportQuality": 0.8,
						"fileType": "image/png",
						"imageSpriteId": 4208881,
						"useCollisionPoly": true,
						"duration": 1,
						"tag": ""
					},
					{
						"width": 48,
						"height": 48,
						"originX": 0.5,
						"originY": 0.8125,
						"originalSource": "",
						"exportFormat": "lossless",
						"exportQuality": 0.8,
						"fileType": "image/png",
						"imageSpriteId": 5909374,
						"useCollisionPoly": true,
						"duration": 1,
						"tag": ""
					},
					{
						"width": 48,
						"height": 48,
						"originX": 0.5,
						"originY": 0.8125,
						"originalSource": "",
						"exportFormat": "lossless",
						"exportQuality": 0.8,
						"fileType": "image/png",
						"imageSpriteId": 8571628,
						"useCollisionPoly": true,
						"duration": 1,
						"tag": ""
					},
					{
						"width": 48,
						"height": 48,
						"originX": 0.5,
						"originY": 0.8125,
						"originalSource": "",
						"exportFormat": "lossless",
						"exportQuality": 0.8,
						"fileType": "image/png",
						"imageSpriteId": 3171534,
						"useCollisionPoly": true,
						"duration": 1,
						"tag": ""
					}
				],
				"sid": 794135520993845,
				"name": "Walk_Up",
				"isLooping": true,
				"isPingPong": false,
				"repeatCount": 1,
				"repeatTo": 0,
				"speed": 13
			},
			{
				"frames": [
					{
						"width": 48,
						"height": 48,
						"originX": 0.5,
						"originY": 0.8125,
						"originalSource": "",
						"exportFormat": "lossless",
						"exportQuality": 0.8,
						"fileType": "image/png",
						"imageSpriteId": 4753910,
						"useCollisionPoly": true,
						"duration": 1,
						"tag": ""
					},
					{
						"width": 48,
						"height": 48,
						"originX": 0.5,
						"originY": 0.8125,
						"originalSource": "",
						"exportFormat": "lossless",
						"exportQuality": 0.8,
						"fileType": "image/png",
						"imageSpriteId": 5949748,
						"useCollisionPoly": true,
						"duration": 1,
						"tag": ""
					},
					{
						"width": 48,
						"height": 48,
						"originX": 0.5,
						"originY": 0.8125,
						"originalSource": "",
						"exportFormat": "lossless",
						"exportQuality": 0.8,
						"fileType": "image/png",
						"imageSpriteId": 8821578,
						"useCollisionPoly": true,
						"duration": 1,
						"tag": ""
					},
					{
						"width": 48,
						"height": 48,
						"originX": 0.5,
						"originY": 0.8125,
						"originalSource": "",
						"exportFormat": "lossless",
						"exportQuality": 0.8,
						"fileType": "image/png",
						"imageSpriteId": 7612862,
						"useCollisionPoly": true,
						"duration": 1,
						"tag": ""
					}
				],
				"sid": 344398318992501,
				"name": "Walk_Down",
				"isLooping": true,
				"isPingPong": false,
				"repeatCount": 1,
				"repeatTo": 0,
				"speed": 13
			},
			{
				"frames": [
					{
						"width": 48,
						"height": 48,
						"originX": 0.5,
						"originY": 0.8125,
						"originalSource": "",
						"exportFormat": "lossless",
						"exportQuality": 0.8,
						"fileType": "image/png",
						"imageSpriteId": 5823038,
						"useCollisionPoly": true,
						"duration": 1,
						"tag": ""
					},
					{
						"width": 48,
						"height": 48,
						"originX": 0.5,
						"originY": 0.8125,
						"originalSource": "",
						"exportFormat": "lossless",
						"exportQuality": 0.8,
						"fileType": "image/png",
						"imageSpriteId": 8942647,
						"useCollisionPoly": true,
						"duration": 1,
						"tag": ""
					},
					{
						"width": 48,
						"height": 48,
						"originX": 0.5,
						"originY": 0.8125,
						"originalSource": "",
						"exportFormat": "lossless",
						"exportQuality": 0.8,
						"fileType": "image/png",
						"imageSpriteId": 6343368,
						"useCollisionPoly": true,
						"duration": 1,
						"tag": ""
					},
					{
						"width": 48,
						"height": 48,
						"originX": 0.5,
						"originY": 0.8125,
						"originalSource": "",
						"exportFormat": "lossless",
						"exportQuality": 0.8,
						"fileType": "image/png",
						"imageSpriteId": 2628035,
						"useCollisionPoly": true,
						"duration": 1,
						"tag": ""
					}
				],
				"sid": 330997838456505,
				"name": "Attack_Left",
				"isLooping": false,
				"isPingPong": false,
				"repeatCount": 1,
				"repeatTo": 0,
				"speed": 15
			},
			{
				"frames": [
					{
						"width": 48,
						"height": 48,
						"originX": 0.5,
						"originY": 0.8125,
						"originalSource": "",
						"exportFormat": "lossless",
						"exportQuality": 0.8,
						"fileType": "image/png",
						"imageSpriteId": 8435776,
						"collisionPoly": {
							"points": [
								1,
								1,
								0,
								1,
								0,
								0,
								1,
								0
							]
						},
						"useCollisionPoly": true,
						"duration": 1,
						"tag": ""
					},
					{
						"width": 48,
						"height": 48,
						"originX": 0.5,
						"originY": 0.8125,
						"originalSource": "",
						"exportFormat": "lossless",
						"exportQuality": 0.8,
						"fileType": "image/png",
						"imageSpriteId": 2196706,
						"collisionPoly": {
							"points": [
								1,
								1,
								0,
								1,
								0,
								0,
								1,
								0
							]
						},
						"useCollisionPoly": true,
						"duration": 1,
						"tag": ""
					},
					{
						"width": 48,
						"height": 48,
						"originX": 0.5,
						"originY": 0.8125,
						"originalSource": "",
						"exportFormat": "lossless",
						"exportQuality": 0.8,
						"fileType": "image/png",
						"imageSpriteId": 3059415,
						"collisionPoly": {
							"points": [
								1,
								1,
								0,
								1,
								0,
								0,
								1,
								0
							]
						},
						"useCollisionPoly": true,
						"duration": 1,
						"tag": ""
					},
					{
						"width": 48,
						"height": 48,
						"originX": 0.5,
						"originY": 0.8125,
						"originalSource": "",
						"exportFormat": "lossless",
						"exportQuality": 0.8,
						"fileType": "image/png",
						"imageSpriteId": 1614610,
						"collisionPoly": {
							"points": [
								1,
								1,
								0,
								1,
								0,
								0,
								1,
								0
							]
						},
						"useCollisionPoly": true,
						"duration": 1,
						"tag": ""
					}
				],
				"sid": 873072173866755,
				"name": "Attack_Right",
				"isLooping": false,
				"isPingPong": false,
				"repeatCount": 1,
				"repeatTo": 0,
				"speed": 15
			},
			{
				"frames": [
					{
						"width": 48,
						"height": 48,
						"originX": 0.5,
						"originY": 0.8125,
						"originalSource": "",
						"exportFormat": "lossless",
						"exportQuality": 0.8,
						"fileType": "image/png",
						"imageSpriteId": 294040,
						"useCollisionPoly": true,
						"duration": 1,
						"tag": ""
					},
					{
						"width": 48,
						"height": 48,
						"originX": 0.5,
						"originY": 0.8125,
						"originalSource": "",
						"exportFormat": "lossless",
						"exportQuality": 0.8,
						"fileType": "image/png",
						"imageSpriteId": 244498,
						"useCollisionPoly": true,
						"duration": 1,
						"tag": ""
					},
					{
						"width": 48,
						"height": 48,
						"originX": 0.5,
						"originY": 0.8125,
						"originalSource": "",
						"exportFormat": "lossless",
						"exportQuality": 0.8,
						"fileType": "image/png",
						"imageSpriteId": 1933231,
						"useCollisionPoly": true,
						"duration": 1,
						"tag": ""
					},
					{
						"width": 48,
						"height": 48,
						"originX": 0.5,
						"originY": 0.8125,
						"originalSource": "",
						"exportFormat": "lossless",
						"exportQuality": 0.8,
						"fileType": "image/png",
						"imageSpriteId": 4635495,
						"useCollisionPoly": true,
						"duration": 1,
						"tag": ""
					}
				],
				"sid": 376376776206006,
				"name": "Attack_Up",
				"isLooping": false,
				"isPingPong": false,
				"repeatCount": 1,
				"repeatTo": 0,
				"speed": 15
			},
			{
				"frames": [
					{
						"width": 48,
						"height": 48,
						"originX": 0.5,
						"originY": 0.8125,
						"originalSource": "",
						"exportFormat": "lossless",
						"exportQuality": 0.8,
						"fileType": "image/png",
						"imageSpriteId": 1202876,
						"useCollisionPoly": true,
						"duration": 1,
						"tag": ""
					},
					{
						"width": 48,
						"height": 48,
						"originX": 0.5,
						"originY": 0.8125,
						"originalSource": "",
						"exportFormat": "lossless",
						"exportQuality": 0.8,
						"fileType": "image/png",
						"imageSpriteId": 5850415,
						"useCollisionPoly": true,
						"duration": 1,
						"tag": ""
					},
					{
						"width": 48,
						"height": 48,
						"originX": 0.5,
						"originY": 0.8125,
						"originalSource": "",
						"exportFormat": "lossless",
						"exportQuality": 0.8,
						"fileType": "image/png",
						"imageSpriteId": 2458312,
						"useCollisionPoly": true,
						"duration": 1,
						"tag": ""
					}
				],
				"sid": 727523752594658,
				"name": "Attack_Down",
				"isLooping": false,
				"isPingPong": false,
				"repeatCount": 1,
				"repeatTo": 0,
				"speed": 15
			},
			{
				"frames": [
					{
						"width": 48,
						"height": 48,
						"originX": 0.5,
						"originY": 0.8125,
						"originalSource": "",
						"exportFormat": "lossless",
						"exportQuality": 0.8,
						"fileType": "image/png",
						"imageSpriteId": 5738937,
						"useCollisionPoly": true,
						"duration": 1,
						"tag": ""
					},
					{
						"width": 48,
						"height": 48,
						"originX": 0.5,
						"originY": 0.8125,
						"originalSource": "",
						"exportFormat": "lossless",
						"exportQuality": 0.8,
						"fileType": "image/png",
						"imageSpriteId": 2889819,
						"useCollisionPoly": true,
						"duration": 1,
						"tag": ""
					}
				],
				"sid": 831115784372237,
				"name": "Hurt_Left",
				"isLooping": false,
				"isPingPong": false,
				"repeatCount": 1,
				"repeatTo": 0,
				"speed": 5
			},
			{
				"frames": [
					{
						"width": 48,
						"height": 48,
						"originX": 0.5,
						"originY": 0.8125,
						"originalSource": "",
						"exportFormat": "lossless",
						"exportQuality": 0.8,
						"fileType": "image/png",
						"imageSpriteId": 3842174,
						"useCollisionPoly": true,
						"duration": 1,
						"tag": ""
					},
					{
						"width": 48,
						"height": 48,
						"originX": 0.5,
						"originY": 0.8125,
						"originalSource": "",
						"exportFormat": "lossless",
						"exportQuality": 0.8,
						"fileType": "image/png",
						"imageSpriteId": 4478332,
						"useCollisionPoly": true,
						"duration": 1,
						"tag": ""
					}
				],
				"sid": 648983498736675,
				"name": "Hurt_Right",
				"isLooping": false,
				"isPingPong": false,
				"repeatCount": 1,
				"repeatTo": 0,
				"speed": 5
			},
			{
				"frames": [
					{
						"width": 48,
						"height": 48,
						"originX": 0.5,
						"originY": 0.8125,
						"originalSource": "",
						"exportFormat": "lossless",
						"exportQuality": 0.8,
						"fileType": "image/png",
						"imageSpriteId": 9036713,
						"useCollisionPoly": true,
						"duration": 1,
						"tag": ""
					},
					{
						"width": 48,
						"height": 48,
						"originX": 0.5,
						"originY": 0.8125,
						"originalSource": "",
						"exportFormat": "lossless",
						"exportQuality": 0.8,
						"fileType": "image/png",
						"imageSpriteId": 6407850,
						"useCollisionPoly": true,
						"duration": 1,
						"tag": ""
					}
				],
				"sid": 856313433020512,
				"name": "Hurt_Up",
				"isLooping": false,
				"isPingPong": false,
				"repeatCount": 1,
				"repeatTo": 0,
				"speed": 5
			},
			{
				"frames": [
					{
						"width": 48,
						"height": 48,
						"originX": 0.5,
						"originY": 0.8125,
						"originalSource": "",
						"exportFormat": "lossless",
						"exportQuality": 0.8,
						"fileType": "image/png",
						"imageSpriteId": 5593709,
						"useCollisionPoly": true,
						"duration": 1,
						"tag": ""
					},
					{
						"width": 48,
						"height": 48,
						"originX": 0.5,
						"originY": 0.8125,
						"originalSource": "",
						"exportFormat": "lossless",
						"exportQuality": 0.8,
						"fileType": "image/png",
						"imageSpriteId": 9621326,
						"useCollisionPoly": true,
						"duration": 1,
						"tag": ""
					}
				],
				"sid": 404826262553798,
				"name": "Hurt_Down",
				"isLooping": false,
				"isPingPong": false,
				"repeatCount": 1,
				"repeatTo": 0,
				"speed": 5
			}
		],
		"subfolders": []
	}
}